{
    "variants": {
        "axis=y,variant=copper": { "model": "hm:log_copper" },
        "axis=z,variant=copper": { "model": "hm:log_copper", "x": 90 },
        "axis=x,variant=copper": { "model": "hm:log_copper", "x": 90, "y": 90 },
        "axis=none,variant=copper": { "model": "hm:log_copper" },
        "axis=y,variant=aluminium": { "model": "hm:log_aluminium" },
        "axis=z,variant=aluminium": { "model": "hm:log_aluminium", "x": 90 },
        "axis=x,variant=aluminium": { "model": "hm:log_aluminium", "x": 90, "y": 90 },
        "axis=none,variant=aluminium": { "model": "hm:log_aluminium" }
    }
}
